src/__init__.py
src/checkFile.py
src/checkThatLink.py
src/colorText.py
src/parseUrl.py
tests/__init__.py
tests/test_checkFile.py
tests/test_checkThatLink.py
Check_That_Link-1.0.0.dist-info/LICENSE
Check_That_Link-1.0.0.dist-info/METADATA
Check_That_Link-1.0.0.dist-info/WHEEL
Check_That_Link-1.0.0.dist-info/entry_points.txt
Check_That_Link-1.0.0.dist-info/top_level.txt
Check_That_Link-1.0.0.dist-info/RECORD
