Metadata-Version: 2.1
Name: Check-That-Link
Version: 1.0.0
Summary: Command-line tool for checking te status of links stored in a file.
Home-page: https://github.com/TDDR/checkThatLink
Author: Tim Roberts
Author-email: tims@email.com
License: UNKNOWN
Platform: UNKNOWN
Classifier: Programming Language :: Python :: 3
Classifier: License :: OSI Approved :: MIT License
Classifier: Operating System :: OS Independent
Requires-Python: >=3.6
Requires-Dist: argparse (==1.4.0)
Requires-Dist: urllib3 (==1.25.11)
Requires-Dist: black (==20.8b1)
Requires-Dist: flake8 (==3.8.4)
Requires-Dist: pytest (==6.1.2)
Requires-Dist: pytest-cov (==2.10.1)
